{
  "type": "FeatureCollection",
  "features": [
    {
      "type": "Feature",
      "properties": {
        "id": "demo-camp-1",
        "name": "Alpine Base Camp",
        "description": "Stunning mountain views with excellent network coverage",
        "rating": 4.5,
        "priceRange": "moderate",
        "capacity": 50,
        "amenities": ["wifi", "restrooms", "showers", "electricity"],
        "tags": ["mountain", "scenic", "hiking"],
        "lastUpdated": "2024-01-15T10:00:00Z"
      },
      "geometry": {
        "type": "Point",
        "coordinates": [11.4041, 47.2692]
      }
    },
    {
      "type": "Feature", 
      "properties": {
        "id": "demo-camp-2",
        "name": "Forest Haven",
        "description": "Peaceful forest camping with basic amenities",
        "rating": 4.0,
        "priceRange": "budget",
        "capacity": 30,
        "amenities": ["restrooms", "fire_pit"],
        "tags": ["forest", "quiet", "nature"],
        "lastUpdated": "2024-01-10T15:30:00Z"
      },
      "geometry": {
        "type": "Point",
        "coordinates": [13.4050, 52.5200]
      }
    },
    {
      "type": "Feature",
      "properties": {
        "id": "demo-camp-3", 
        "name": "Lake View Resort",
        "description": "Premium lakeside camping with full amenities",
        "rating": 4.8,
        "priceRange": "premium",
        "capacity": 100,
        "amenities": ["wifi", "restrooms", "showers", "electricity", "restaurant", "boat_rental"],
        "tags": ["lake", "premium", "water_sports", "family"],
        "lastUpdated": "2024-01-20T09:15:00Z"
      },
      "geometry": {
        "type": "Point", 
        "coordinates": [7.8537, 47.9990]
      }
    }
  ]
}